vectorspace/__init__.py
vectorspace/conceptnet.py
vectorspace/embedding.py
vectorspace/fasttext.py
vectorspace/lmdb.py
vectorspace/locks.py
vectorspace/logger.py
vectorspace/mapping.py
vectorspace/math.py
vectorspace/numba.py
vectorspace/plot.py
vectorspace/query.py
vectorspace/spacy.py
vectorspace/store.py
vectorspace/text.py
vectorspace/utils.py
vectorspace/word2vec.py
vectorspace/zoomable_scatter.json
vectorspace-1.1.0.dist-info/LICENSE
vectorspace-1.1.0.dist-info/METADATA
vectorspace-1.1.0.dist-info/WHEEL
vectorspace-1.1.0.dist-info/top_level.txt
vectorspace-1.1.0.dist-info/zip-safe
vectorspace-1.1.0.dist-info/RECORD
